raxe/__init__.py
raxe/py.typed
raxe/application/__init__.py
raxe/application/ab_testing.py
raxe/application/apply_policy.py
raxe/application/eager_l2.py
raxe/application/preloader.py
raxe/application/scan_merger.py
raxe/application/scan_pipeline.py
raxe/application/scan_pipeline_async.py
raxe/application/session_tracker.py
raxe/application/telemetry_manager.py
raxe/application/telemetry_orchestrator.py
raxe/application/tenant_exceptions.py
raxe/application/tenant_service.py
raxe/application/analytics/__init__.py
raxe/application/analytics/achievement_service.py
raxe/application/analytics/repositories.py
raxe/application/analytics/retention_service.py
raxe/application/analytics/statistics_service.py
raxe/application/analytics/streak_service.py
raxe/async_sdk/__init__.py
raxe/async_sdk/cache.py
raxe/async_sdk/client.py
raxe/async_sdk/wrappers/__init__.py
raxe/async_sdk/wrappers/openai.py
raxe/cli/__init__.py
raxe/cli/app.py
raxe/cli/auth.py
raxe/cli/auth_progress.py
raxe/cli/branding.py
raxe/cli/config.py
raxe/cli/custom_rules.py
raxe/cli/doctor.py
raxe/cli/error_handler.py
raxe/cli/event.py
raxe/cli/exit_codes.py
raxe/cli/expiry_warning.py
raxe/cli/export.py
raxe/cli/help.py
raxe/cli/history.py
raxe/cli/l2_formatter.py
raxe/cli/main.py
raxe/cli/models.py
raxe/cli/output.py
raxe/cli/policy.py
raxe/cli/privacy.py
raxe/cli/profiler.py
raxe/cli/progress.py
raxe/cli/progress_context.py
raxe/cli/repl.py
raxe/cli/rules.py
raxe/cli/setup_wizard.py
raxe/cli/stats.py
raxe/cli/suppress.py
raxe/cli/telemetry.py
raxe/cli/tenant.py
raxe/cli/terminal_context.py
raxe/cli/test.py
raxe/cli/tune.py
raxe/cli/validate.py
raxe/domain/__init__.py
raxe/domain/inline_suppression.py
raxe/domain/models.py
raxe/domain/suppression.py
raxe/domain/suppression_factory.py
raxe/domain/analytics/__init__.py
raxe/domain/analytics/achievements.py
raxe/domain/analytics/models.py
raxe/domain/analytics/retention.py
raxe/domain/analytics/statistics.py
raxe/domain/analytics/streaks.py
raxe-0.7.1.dist-info/licenses/LICENSE
raxe-0.7.1.dist-info/METADATA
raxe-0.7.1.dist-info/WHEEL
raxe-0.7.1.dist-info/entry_points.txt
raxe-0.7.1.dist-info/top_level.txt
raxe-0.7.1.dist-info/RECORD
