Metadata-Version: 2.4
Name: raxe
Version: 0.7.1
Summary: RAXE Community Edition - AI Security for Everyone. 460+ threat detection rules, L2 CPU-based ML, always free.
Author-email: "RAXE Technologies, Inc." <hello@raxe.ai>
License: Proprietary - See LICENSE file
Project-URL: Homepage, https://raxe.ai
Project-URL: Documentation, https://docs.raxe.ai
Project-URL: Repository, https://github.com/raxe-ai/raxe-ce
Project-URL: Bug Tracker, https://github.com/raxe-ai/raxe-ce/issues
Project-URL: Enterprise Edition, https://raxe.ai/enterprise
Project-URL: Schedule Demo, https://raxe.ai/demo
Keywords: ai-security,llm-security,prompt-injection,threat-detection,ml-security,community-edition,privacy-first
Classifier: Development Status :: 4 - Beta
Classifier: Intended Audience :: Developers
Classifier: Intended Audience :: Science/Research
Classifier: Topic :: Security
Classifier: Topic :: Software Development :: Libraries :: Python Modules
Classifier: Programming Language :: Python :: 3
Classifier: Programming Language :: Python :: 3.10
Classifier: Programming Language :: Python :: 3.11
Classifier: Programming Language :: Python :: 3.12
Classifier: Operating System :: OS Independent
Requires-Python: >=3.10
License-File: LICENSE
Requires-Dist: click<9.0,>=8.0
Requires-Dist: pydantic<3.0,>=2.0
Requires-Dist: httpx<1.0,>=0.24
Requires-Dist: structlog<25.0,>=23.0
Requires-Dist: sqlalchemy<3.0,>=2.0
Requires-Dist: pyyaml<7.0,>=6.0
Requires-Dist: rich<14.0,>=13.0
Requires-Dist: tomli<3.0,>=2.0; python_version < "3.11"
Requires-Dist: jsonschema<5.0,>=4.17
Requires-Dist: regex<2026.0,>=2024.0.0
Requires-Dist: onnxruntime<2.0,>=1.16.0
Requires-Dist: sentence-transformers<3.0,>=2.2.0
Requires-Dist: numpy<2.0,>=1.24.0
Requires-Dist: scikit-learn<1.8.0,>=1.7.0
Provides-Extra: dev
Requires-Dist: pytest>=7.4; extra == "dev"
Requires-Dist: pytest-cov>=4.1; extra == "dev"
Requires-Dist: pytest-asyncio>=0.21; extra == "dev"
Requires-Dist: pytest-benchmark>=4.0; extra == "dev"
Requires-Dist: pytest-xdist>=3.0; extra == "dev"
Requires-Dist: ruff>=0.1.0; extra == "dev"
Requires-Dist: mypy>=1.5; extra == "dev"
Requires-Dist: pre-commit>=3.3; extra == "dev"
Requires-Dist: black>=23.0; extra == "dev"
Requires-Dist: types-pyyaml; extra == "dev"
Requires-Dist: types-requests; extra == "dev"
Requires-Dist: build>=1.0; extra == "dev"
Provides-Extra: repl
Requires-Dist: prompt-toolkit<4.0,>=3.0; extra == "repl"
Provides-Extra: config-tools
Requires-Dist: tomli-w<2.0,>=1.0; extra == "config-tools"
Provides-Extra: wrappers
Requires-Dist: openai>=1.0; extra == "wrappers"
Requires-Dist: anthropic>=0.5; extra == "wrappers"
Provides-Extra: langchain
Requires-Dist: langchain>=0.1; extra == "langchain"
Requires-Dist: langchain-core>=0.1; extra == "langchain"
Provides-Extra: crewai
Requires-Dist: crewai>=0.30; extra == "crewai"
Provides-Extra: autogen
Requires-Dist: pyautogen>=0.2; extra == "autogen"
Provides-Extra: llamaindex
Requires-Dist: llama-index-core>=0.10; extra == "llamaindex"
Provides-Extra: litellm
Requires-Dist: litellm>=1.0; extra == "litellm"
Provides-Extra: dspy
Requires-Dist: dspy>=2.0; extra == "dspy"
Provides-Extra: portkey
Requires-Dist: openai>=1.0; extra == "portkey"
Provides-Extra: agents
Requires-Dist: langchain>=0.1; extra == "agents"
Requires-Dist: langchain-core>=0.1; extra == "agents"
Requires-Dist: crewai>=0.30; extra == "agents"
Requires-Dist: pyautogen>=0.2; extra == "agents"
Requires-Dist: llama-index-core>=0.10; extra == "agents"
Requires-Dist: litellm>=1.0; extra == "agents"
Requires-Dist: dspy>=2.0; extra == "agents"
Provides-Extra: all
Requires-Dist: openai>=1.0; extra == "all"
Requires-Dist: anthropic>=0.5; extra == "all"
Requires-Dist: langchain>=0.1; extra == "all"
Requires-Dist: langchain-core>=0.1; extra == "all"
Requires-Dist: crewai>=0.30; extra == "all"
Requires-Dist: pyautogen>=0.2; extra == "all"
Requires-Dist: llama-index-core>=0.10; extra == "all"
Requires-Dist: litellm>=1.0; extra == "all"
Requires-Dist: dspy>=2.0; extra == "all"
Requires-Dist: prompt-toolkit<4.0,>=3.0; extra == "all"
Requires-Dist: tomli-w<2.0,>=1.0; extra == "all"
Dynamic: license-file
